{
  "main": [
    { "name": "Home", "url": "/" },
    { "name": "Models", "url": "/models" },
    { "name": "Blog", "url": "/blog" },
    { "name": "Docs", "url": "https://docs.rifx.online" }
  ],
  "footer": [
    { "name": "About", "url": "/about" },
    { "name": "Contact", "url": "/contact" },
    { "name": "Privacy Policy", "url": "/privacy-policy" },
    { "name": "Tags", "url": "/tags" }
    
  ],
  "models": [
    { "name": "About", "url": "/about" },
    { "name": "Contact", "url": "/contact" },
    { "name": "Elements", "url": "/elements" },
    { "name": "Authors", "url": "/authors" },
    { "name": "Privacy Policy", "url": "/privacy-policy" },
    { "name": "Tags", "url": "/tags" }
  ]
}
